{
  "name": "vpplus",
  "version": "1.0.0",
  "license": "ISC",
  "type": "module",
  "scripts": {
    "dev": "vite dev ",
    "preview": "vite preview",
    "build": "vite build ",
    "generate": "vite-ssg build",
    "test": "node test.js",
    "serve": "ws -p 5000 -d dist -s index.html",
    "clean": "rm -Rf dist extras"
  },
  "dependencies": {
    "@headlessui/vue": "^1.6.7",
    "firebase": "^9.9.0",
    "pinia": "^2.0.16",
    "vue": "^3.2.37",
    "vue-i18n": "^9.1.10",
    "vue-router": "^4.1.2"
  },
  "devDependencies": {
    "@fortawesome/fontawesome-svg-core": "^6.1.1",
    "@fortawesome/free-brands-svg-icons": "^6.1.1",
    "@fortawesome/free-regular-svg-icons": "^6.1.1",
    "@fortawesome/free-solid-svg-icons": "^6.1.1",
    "@fortawesome/vue-fontawesome": "^2.0.8",
    "@intlify/vite-plugin-vue-i18n": "^5.0.0",
    "@originjs/vite-plugin-content": "^1.0.1",
    "@tailwindcss/forms": "^0.5.2",
    "@tailwindcss/line-clamp": "^0.4.0",
    "@tailwindcss/typography": "^0.5.4",
    "@vitejs/plugin-vue": "^3.0.1",
    "@vueuse/head": "^0.7.6",
    "autoprefixer": "^10.4.7",
    "daisyui": "^2.19.0",
    "happy-dom": "^6.0.4",
    "markdown-it": "^13.0.1",
    "postcss": "^8.4.14",
    "prismjs": "^1.28.0",
    "pug": "^3.0.2",
    "sass": "^1.53.0",
    "tailwindcss": "^3.1.6",
    "unplugin-auto-import": "^0.9.3",
    "unplugin-vue-components": "^0.21.1",
    "vite": "^3.0.2",
    "vite-plugin-inspect": "^0.6.0",
    "vite-plugin-md": "^0.18.1",
    "vite-plugin-pages": "^0.25.0",
    "vite-plugin-pages-sitemap": "^1.2.2",
    "vite-plugin-pwa": "^0.12.3",
    "vite-plugin-vue-layouts": "^0.6.0",
    "vite-ssg": "^0.20.2",
    "vite-ssg-sitemap": "^0.3.1"
  },
  "unused": {
    "vitepress": "1.0.0-alpha.4"
  }
}
